django_currency_exchange
