Metadata-Version: 1.0
Name: django-currency-exchange
Version: 0.2.0
Summary: Django Foreign Exchange
Home-page: https://github.com/gizmag/django-currency-exchange
Author: Gizmag
Author-email: tech@gizmag.com
License: UNKNOWN
Platform: UNKNOWN
